<?xml version="1.0" encoding="utf-8"?>
<class id="2a309fb2-c487-4c00-9462-16dac9824731" type="Association Settings" typeId="16d21684-d5ea-4fde-b648-f88d292fa272">
  <name>Show Dialog</name>
  <display>Show Dialog</display>
  <isAbstract>false</isAbstract>
  <sort-children>by-type-then-by-name</sort-children>
  <genericTypes />
  <isMapped>false</isMapped>
  <parentFolderId>3cd798f0-8cdf-42a4-b733-469632a86f27</parentFolderId>
  <packageId>a2a95421-3e55-43c7-96ad-355610b43c4d</packageId>
  <packageName>Intent.Modelers.UI.Core</packageName>
  <stereotypes />
  <metadata />
  <childElements>
    <childElement id="ad3de626-cb72-4dde-966b-122a6b386fb7" type="Association Source End Settings" typeId="32aac8b7-3eac-4a15-87cb-7fb98fdfdf37">
      <name>Show Dialog Source End</name>
      <display>Show Dialog Source End</display>
      <isAbstract>false</isAbstract>
      <genericTypes />
      <isMapped>false</isMapped>
      <parentFolderId>2a309fb2-c487-4c00-9462-16dac9824731</parentFolderId>
      <packageId>a2a95421-3e55-43c7-96ad-355610b43c4d</packageId>
      <packageName>Intent.Modelers.UI.Core</packageName>
      <stereotypes>
        <stereotype stereotypeDefinitionId="5a410b57-e6a8-4567-b387-71a89290b2c9" name="Settings">
          <addedByDefault>true</addedByDefault>
          <definitionPackageName>Intent.ModuleBuilder</definitionPackageName>
          <definitionPackageId>9972b2a9-b749-4bba-b5c8-824bf694c6ef</definitionPackageId>
          <properties>
            <property name="dc56596e-b1bd-40d1-ae5e-5aee967fed36" display="Icon" isActive="true" />
            <property name="763a1f02-cdc2-4b43-a763-5ff38d59af60" display="Target Types" value="[&quot;e030c97a-e066-40a7-8188-808c275df3cb&quot;]" isActive="true" />
            <property name="fde5c705-2274-4536-9d47-62029793629d" display="Target Traits" value="[]" isActive="true" />
            <property name="b534060a-c8a3-4631-b4a9-db0baeecd1b3" display="Api Property Name" isActive="true" />
            <property name="65b99db7-ec8e-408d-a0fd-a98245d1fbcc" display="Display Text Function" value="" isActive="true" />
            <property name="6bf94b78-382a-4002-ac88-a569b59e16e6" display="Name Accessibility" value="Hidden" isActive="true" />
            <property name="5e68cf49-e0f7-461a-8f5a-436a5ec91060" display="Default Name Function" value="" isActive="true" />
            <property name="2d07ed88-82bf-4d30-9280-1488f0f927e0" display="Name Must Be Unique" value="true" isActive="true" />
            <property name="c81dddd3-8e13-4fe9-b923-1ad339b30746" display="Is Navigable Enabled" value="true" isActive="true" />
            <property name="9419ab85-5421-4b54-82f2-da502a9651d6" display="Is Nullable Enabled" value="true" isActive="true" />
            <property name="9b861271-feb0-4d57-ae86-7e053ed441ae" display="Is Collection Enabled" value="true" isActive="true" />
            <property name="18131f3e-1c29-4c21-a32a-3946204d0d29" display="Is Navigable Default" value="true" isActive="true" />
            <property name="b1f32c0b-f45f-4cdb-9a4e-ff989f9111e0" display="Is Nullable Default" value="false" isActive="true" />
            <property name="bb49808b-06e1-45f1-9f6b-08dede577305" display="Is Collection Default" value="false" isActive="true" />
            <property name="77a800bb-e76a-4b1d-bbc1-32cf7baed608" display="Allow Multiple" value="true" isActive="true" />
            <property name="a9703eab-0aa4-4c3f-ab68-f9ccba205e5a" display="Allow Sorting" value="true" isActive="true" />
            <property name="9ae87826-7f34-4cab-b371-5cd2da9331dd" display="Sort Children" isActive="true" />
          </properties>
        </stereotype>
      </stereotypes>
      <metadata />
      <childElements />
    </childElement>
    <childElement id="c44a7969-abfa-4073-ab2c-d2d0f1f6bd2f" type="Association Destination End Settings" typeId="c4c61fdc-464d-41d2-8e0e-5a734d588302">
      <name>Show Dialog Target End</name>
      <display>Show Dialog Target End</display>
      <isAbstract>false</isAbstract>
      <sort-children>by-type-then-by-name</sort-children>
      <genericTypes />
      <isMapped>false</isMapped>
      <parentFolderId>2a309fb2-c487-4c00-9462-16dac9824731</parentFolderId>
      <packageId>a2a95421-3e55-43c7-96ad-355610b43c4d</packageId>
      <packageName>Intent.Modelers.UI.Core</packageName>
      <stereotypes>
        <stereotype stereotypeDefinitionId="5a410b57-e6a8-4567-b387-71a89290b2c9" name="Settings">
          <addedByDefault>true</addedByDefault>
          <definitionPackageName>Intent.ModuleBuilder</definitionPackageName>
          <definitionPackageId>9972b2a9-b749-4bba-b5c8-824bf694c6ef</definitionPackageId>
          <properties>
            <property name="dc56596e-b1bd-40d1-ae5e-5aee967fed36" display="Icon" isActive="true" />
            <property name="763a1f02-cdc2-4b43-a763-5ff38d59af60" display="Target Types" value="[&quot;b1c481e1-e91e-4c29-9817-00ab9cad4b6b&quot;]" isActive="true" />
            <property name="fde5c705-2274-4536-9d47-62029793629d" display="Target Traits" value="[]" isActive="true" />
            <property name="b534060a-c8a3-4631-b4a9-db0baeecd1b3" display="Api Property Name" isActive="true" />
            <property name="65b99db7-ec8e-408d-a0fd-a98245d1fbcc" display="Display Text Function" value="" isActive="true" />
            <property name="6bf94b78-382a-4002-ac88-a569b59e16e6" display="Name Accessibility" value="Optional" isActive="true" />
            <property name="5e68cf49-e0f7-461a-8f5a-436a5ec91060" display="Default Name Function" value="" isActive="true" />
            <property name="2d07ed88-82bf-4d30-9280-1488f0f927e0" display="Name Must Be Unique" value="true" isActive="true" />
            <property name="c81dddd3-8e13-4fe9-b923-1ad339b30746" display="Is Navigable Enabled" value="true" isActive="true" />
            <property name="9419ab85-5421-4b54-82f2-da502a9651d6" display="Is Nullable Enabled" value="true" isActive="true" />
            <property name="9b861271-feb0-4d57-ae86-7e053ed441ae" display="Is Collection Enabled" value="true" isActive="true" />
            <property name="18131f3e-1c29-4c21-a32a-3946204d0d29" display="Is Navigable Default" value="true" isActive="true" />
            <property name="b1f32c0b-f45f-4cdb-9a4e-ff989f9111e0" display="Is Nullable Default" value="false" isActive="true" />
            <property name="bb49808b-06e1-45f1-9f6b-08dede577305" display="Is Collection Default" value="false" isActive="true" />
            <property name="77a800bb-e76a-4b1d-bbc1-32cf7baed608" display="Allow Multiple" value="true" isActive="true" />
            <property name="a9703eab-0aa4-4c3f-ab68-f9ccba205e5a" display="Allow Sorting" value="true" isActive="true" />
            <property name="9ae87826-7f34-4cab-b371-5cd2da9331dd" display="Sort Children" isActive="true" />
          </properties>
        </stereotype>
        <stereotype stereotypeDefinitionId="dc813928-0ce1-4f66-ae31-b5e5d506b4a3" name="[Invokable]">
          <addedByDefault>false</addedByDefault>
          <definitionPackageName>Intent.Modelers.UI</definitionPackageName>
          <definitionPackageId>5c4628ec-679e-4f3d-afda-137c978deae0</definitionPackageId>
          <properties />
        </stereotype>
      </stereotypes>
      <metadata />
      <childElements>
        <childElement id="19333b17-60a2-453c-9a15-1144953fb0e4" type="Context Menu" typeId="d45e383d-90ba-4b64-aca7-34ca100cea21">
          <name>[context menu]</name>
          <display>[context menu]</display>
          <isAbstract>false</isAbstract>
          <sort-children>manually</sort-children>
          <genericTypes />
          <isMapped>false</isMapped>
          <parentFolderId>c44a7969-abfa-4073-ab2c-d2d0f1f6bd2f</parentFolderId>
          <packageId>a2a95421-3e55-43c7-96ad-355610b43c4d</packageId>
          <packageName>Intent.Modelers.UI.Core</packageName>
          <stereotypes />
          <metadata />
          <childElements>
            <childElement id="3bf7c240-1c2c-4900-8718-0e5ccb4ead4d" type="Mapping Option" typeId="00a1eb98-1fc4-4421-9d1c-8733f6bc2111">
              <name>Manage Mapping</name>
              <display>Manage Mapping: Navigation Mapping</display>
              <isAbstract>false</isAbstract>
              <genericTypes />
              <typeReference id="75b1f442-4a89-49c3-b533-523d0b6f5442">
                <typeId>b4777251-a390-48f0-877a-102069e88a22</typeId>
                <isNavigable>true</isNavigable>
                <isNullable>false</isNullable>
                <isCollection>false</isCollection>
                <isRequired>true</isRequired>
                <typePackageName>Intent.Modelers.UI</typePackageName>
                <typePackageId>5c4628ec-679e-4f3d-afda-137c978deae0</typePackageId>
                <stereotypes />
                <genericTypeParameters />
              </typeReference>
              <isMapped>false</isMapped>
              <parentFolderId>19333b17-60a2-453c-9a15-1144953fb0e4</parentFolderId>
              <packageId>a2a95421-3e55-43c7-96ad-355610b43c4d</packageId>
              <packageName>Intent.Modelers.UI.Core</packageName>
              <stereotypes>
                <stereotype stereotypeDefinitionId="6c209f86-87f6-4fc3-802e-e6e553dfbeca" name="Option Settings">
                  <comment />
                  <addedByDefault>true</addedByDefault>
                  <definitionPackageName>Intent.ModuleBuilder</definitionPackageName>
                  <definitionPackageId>9972b2a9-b749-4bba-b5c8-824bf694c6ef</definitionPackageId>
                  <properties>
                    <property name="69d929bc-dcd7-4c2d-aabc-6f05ab6d83b3" display="Shortcut" isActive="true" />
                    <property name="36d5eeba-2483-450e-b51b-b156836f6d3a" display="Shortcut (macOS)" isActive="true" />
                    <property name="08fac0bc-4cf9-45ec-8362-e452a185efee" display="Type Order" isActive="true" />
                    <property name="5e97216b-6c99-4fa2-971d-575a27f212cc" display="Icon" isActive="true" />
                    <property name="63039244-aaad-49eb-84bf-0396a6dd0fe9" display="Is Option Visible Function" isActive="true" />
                  </properties>
                </stereotype>
              </stereotypes>
              <metadata />
              <childElements />
            </childElement>
          </childElements>
        </childElement>
      </childElements>
    </childElement>
    <childElement id="9f2503b2-db3c-4ce5-abc7-eeed9629e465" type="Association Event Settings" typeId="1bdee938-8569-4fbf-84b4-8522d2cbee32">
      <name>[events]</name>
      <display>[events]</display>
      <isAbstract>false</isAbstract>
      <genericTypes />
      <isMapped>false</isMapped>
      <parentFolderId>2a309fb2-c487-4c00-9462-16dac9824731</parentFolderId>
      <packageId>a2a95421-3e55-43c7-96ad-355610b43c4d</packageId>
      <packageName>Intent.Modelers.UI.Core</packageName>
      <stereotypes />
      <metadata />
      <childElements />
    </childElement>
  </childElements>
</class>