<?xml version="1.0" encoding="utf-8"?>
<class id="8e03e014-4b05-4bdc-998a-70ca718b6f48" type="Folder" typeId="3407a825-1331-4f3f-89a4-901903ed97ce">
  <name>Migrations</name>
  <display>Migrations</display>
  <isAbstract>false</isAbstract>
  <genericTypes />
  <isMapped>false</isMapped>
  <parentFolderId>4608b4e9-66a1-47ce-beea-2c155b3e43cc</parentFolderId>
  <stereotypes />
  <metadata />
  <childElements>
    <childElement id="f5ce2272-ebd1-4bcc-972c-615008826eb0" type="Template Output" typeId="d421c322-7a51-4094-89fa-e5d8a0a97b27">
      <name>Intent.ModuleBuilder.Templates.Migrations.OnInstallMigration</name>
      <display>Intent.ModuleBuilder.Templates.Migrations.OnInstallMigration</display>
      <externalReference>Intent.ModuleBuilder</externalReference>
      <isAbstract>false</isAbstract>
      <genericTypes />
      <isMapped>false</isMapped>
      <parentFolderId>8e03e014-4b05-4bdc-998a-70ca718b6f48</parentFolderId>
      <stereotypes />
      <metadata>
        <entry key="status" value="assigned" />
      </metadata>
      <childElements />
    </childElement>
    <childElement id="7aeedd59-83f1-4cf6-8f81-6ba77ab1898b" type="Template Output" typeId="d421c322-7a51-4094-89fa-e5d8a0a97b27">
      <name>Intent.ModuleBuilder.Templates.Migrations.OnUninstallMigration</name>
      <display>Intent.ModuleBuilder.Templates.Migrations.OnUninstallMigration</display>
      <externalReference>Intent.ModuleBuilder</externalReference>
      <isAbstract>false</isAbstract>
      <genericTypes />
      <isMapped>false</isMapped>
      <parentFolderId>8e03e014-4b05-4bdc-998a-70ca718b6f48</parentFolderId>
      <stereotypes />
      <metadata>
        <entry key="status" value="assigned" />
      </metadata>
      <childElements />
    </childElement>
    <childElement id="ba4ba337-cf19-4bdd-8041-d2fd9e8b356d" type="Template Output" typeId="d421c322-7a51-4094-89fa-e5d8a0a97b27">
      <name>Intent.ModuleBuilder.Templates.Migrations.OnVersionMigration</name>
      <display>Intent.ModuleBuilder.Templates.Migrations.OnVersionMigration</display>
      <externalReference>Intent.ModuleBuilder</externalReference>
      <isAbstract>false</isAbstract>
      <genericTypes />
      <isMapped>false</isMapped>
      <parentFolderId>8e03e014-4b05-4bdc-998a-70ca718b6f48</parentFolderId>
      <stereotypes />
      <metadata>
        <entry key="status" value="assigned" />
      </metadata>
      <childElements />
    </childElement>
  </childElements>
</class>