<?xml version="1.0"?>
<outputLog xmlns:xsi="http://www.w3.org/2001/XMLSchema-instance" xmlns:xsd="http://www.w3.org/2001/XMLSchema">
  <ApplicationId>e1ab92df-e9cd-400f-aa94-35c1037749f1</ApplicationId>
  <FileLogs>
    <FileLog>
      <SolutionRelativeFilePath>..\AspNetWebApi\AspNetWebApi.sln</SolutionRelativeFilePath>
    </FileLog>
    <FileLog>
      <ProjectId>2a1c15fa-aca6-40c9-bab0-79665dadb973</ProjectId>
      <SolutionRelativeFilePath>..\AspNetWebApi\ModuleTests.AspNetWebApi.Api\App_Start\WebApiConfig.cs</SolutionRelativeFilePath>
      <ProjectRelativeFilePath>App_Start/WebApiConfig.cs</ProjectRelativeFilePath>
    </FileLog>
    <FileLog>
      <ProjectId>2a1c15fa-aca6-40c9-bab0-79665dadb973</ProjectId>
      <SolutionRelativeFilePath>..\AspNetWebApi\ModuleTests.AspNetWebApi.Api\Context\WebApiServiceCallContext.cs</SolutionRelativeFilePath>
      <ProjectRelativeFilePath>Context/WebApiServiceCallContext.cs</ProjectRelativeFilePath>
    </FileLog>
    <FileLog>
      <ProjectId>2a1c15fa-aca6-40c9-bab0-79665dadb973</ProjectId>
      <SolutionRelativeFilePath>..\AspNetWebApi\ModuleTests.AspNetWebApi.Api\Controllers\AsyncTestServicesController.cs</SolutionRelativeFilePath>
      <ProjectRelativeFilePath>Controllers/AsyncTestServicesController.cs</ProjectRelativeFilePath>
    </FileLog>
    <FileLog>
      <ProjectId>2a1c15fa-aca6-40c9-bab0-79665dadb973</ProjectId>
      <SolutionRelativeFilePath>..\AspNetWebApi\ModuleTests.AspNetWebApi.Api\Controllers\NormalTestServicesController.cs</SolutionRelativeFilePath>
      <ProjectRelativeFilePath>Controllers/NormalTestServicesController.cs</ProjectRelativeFilePath>
    </FileLog>
    <FileLog>
      <ProjectId>2a1c15fa-aca6-40c9-bab0-79665dadb973</ProjectId>
      <SolutionRelativeFilePath>..\AspNetWebApi\ModuleTests.AspNetWebApi.Api\Filters\ExceptionHandlerFilter.cs</SolutionRelativeFilePath>
      <ProjectRelativeFilePath>Filters/ExceptionHandlerFilter.cs</ProjectRelativeFilePath>
    </FileLog>
    <FileLog>
      <ProjectId>2a1c15fa-aca6-40c9-bab0-79665dadb973</ProjectId>
      <SolutionRelativeFilePath>..\AspNetWebApi\ModuleTests.AspNetWebApi.Api\ModuleTests.AspNetWebApi.Api.csproj</SolutionRelativeFilePath>
      <ProjectRelativeFilePath>ModuleTests.AspNetWebApi.Api.csproj</ProjectRelativeFilePath>
    </FileLog>
    <FileLog>
      <ProjectId>2a1c15fa-aca6-40c9-bab0-79665dadb973</ProjectId>
      <SolutionRelativeFilePath>..\AspNetWebApi\ModuleTests.AspNetWebApi.Api\Properties\AssemblyInfo.cs</SolutionRelativeFilePath>
      <ProjectRelativeFilePath>Properties/AssemblyInfo.cs</ProjectRelativeFilePath>
    </FileLog>
    <FileLog>
      <ProjectId>2a1c15fa-aca6-40c9-bab0-79665dadb973</ProjectId>
      <SolutionRelativeFilePath>..\AspNetWebApi\ModuleTests.AspNetWebApi.Api\Startup.cs</SolutionRelativeFilePath>
      <ProjectRelativeFilePath>Startup.cs</ProjectRelativeFilePath>
    </FileLog>
    <FileLog>
      <ProjectId>2a1c15fa-aca6-40c9-bab0-79665dadb973</ProjectId>
      <SolutionRelativeFilePath>..\AspNetWebApi\ModuleTests.AspNetWebApi.Api\Web.config</SolutionRelativeFilePath>
      <ProjectRelativeFilePath>Web.config</ProjectRelativeFilePath>
    </FileLog>
    <FileLog>
      <ProjectId>4fa77bb9-0d1d-4420-979a-9321d13c33dc</ProjectId>
      <SolutionRelativeFilePath>..\AspNetWebApi\ModuleTests.AspNetWebApi.Application\DTOs\TestDTO.cs</SolutionRelativeFilePath>
      <ProjectRelativeFilePath>DTOs/TestDTO.cs</ProjectRelativeFilePath>
    </FileLog>
    <FileLog>
      <ProjectId>4fa77bb9-0d1d-4420-979a-9321d13c33dc</ProjectId>
      <SolutionRelativeFilePath>..\AspNetWebApi\ModuleTests.AspNetWebApi.Application\ModuleTests.AspNetWebApi.Application.csproj</SolutionRelativeFilePath>
      <ProjectRelativeFilePath>ModuleTests.AspNetWebApi.Application.csproj</ProjectRelativeFilePath>
    </FileLog>
    <FileLog>
      <ProjectId>4fa77bb9-0d1d-4420-979a-9321d13c33dc</ProjectId>
      <SolutionRelativeFilePath>..\AspNetWebApi\ModuleTests.AspNetWebApi.Application\Properties\AssemblyInfo.cs</SolutionRelativeFilePath>
      <ProjectRelativeFilePath>Properties/AssemblyInfo.cs</ProjectRelativeFilePath>
    </FileLog>
    <FileLog>
      <ProjectId>4fa77bb9-0d1d-4420-979a-9321d13c33dc</ProjectId>
      <SolutionRelativeFilePath>..\AspNetWebApi\ModuleTests.AspNetWebApi.Application\ServiceContracts\IAsyncTestServices.cs</SolutionRelativeFilePath>
      <ProjectRelativeFilePath>ServiceContracts/IAsyncTestServices.cs</ProjectRelativeFilePath>
    </FileLog>
    <FileLog>
      <ProjectId>4fa77bb9-0d1d-4420-979a-9321d13c33dc</ProjectId>
      <SolutionRelativeFilePath>..\AspNetWebApi\ModuleTests.AspNetWebApi.Application\ServiceContracts\INormalTestServices.cs</SolutionRelativeFilePath>
      <ProjectRelativeFilePath>ServiceContracts/INormalTestServices.cs</ProjectRelativeFilePath>
    </FileLog>
    <FileLog>
      <ProjectId>4fa77bb9-0d1d-4420-979a-9321d13c33dc</ProjectId>
      <SolutionRelativeFilePath>..\AspNetWebApi\ModuleTests.AspNetWebApi.Application\ServiceImplementation\AsyncTestServices.cs</SolutionRelativeFilePath>
      <ProjectRelativeFilePath>ServiceImplementation/AsyncTestServices.cs</ProjectRelativeFilePath>
    </FileLog>
    <FileLog>
      <ProjectId>4fa77bb9-0d1d-4420-979a-9321d13c33dc</ProjectId>
      <SolutionRelativeFilePath>..\AspNetWebApi\ModuleTests.AspNetWebApi.Application\ServiceImplementation\NormalTestServices.cs</SolutionRelativeFilePath>
      <ProjectRelativeFilePath>ServiceImplementation/NormalTestServices.cs</ProjectRelativeFilePath>
    </FileLog>
  </FileLogs>
</outputLog>